oneneuron/__init__.py
oneneuron/perceptron.py
perceptron_py_srivanoo21-0.0.5.dist-info/LICENSE
perceptron_py_srivanoo21-0.0.5.dist-info/METADATA
perceptron_py_srivanoo21-0.0.5.dist-info/WHEEL
perceptron_py_srivanoo21-0.0.5.dist-info/top_level.txt
perceptron_py_srivanoo21-0.0.5.dist-info/RECORD
