Metadata-Version: 2.1
Name: perceptron-py-srivanoo21
Version: 0.0.5
Summary: it's an impementation of perceptron
Home-page: https://github.com/srivanoo21/perceptron_py
Author: srivanoo21
Author-email: srivanoo21@gmail.com
License: UNKNOWN
Project-URL: Bug Tracker, https://github.com/srivanoo21/perceptron_py/issues
Platform: UNKNOWN
Classifier: Programming Language :: Python :: 3
Classifier: License :: OSI Approved :: MIT License
Classifier: Operating System :: OS Independent
Requires-Python: >=3.7
License-File: LICENSE
Requires-Dist: numpy
Requires-Dist: tqdm
